mplcyberpunk/__init__.py
mplcyberpunk/core.py
mplcyberpunk/data/cyberpunk.mplstyle
mplcyberpunk-0.7.5.dist-info/METADATA
mplcyberpunk-0.7.5.dist-info/WHEEL
mplcyberpunk-0.7.5.dist-info/RECORD
