Metadata-Version: 2.3
Name: mplcyberpunk
Version: 0.7.5
Summary: Add-on for Matplotlib to produce 'Cyberpunk' style plots
Project-URL: Homepage, https://github.com/dhaitz/mplcyberpunk
Author-email: Dominik Haitz <dominik.haitz@gmx.de>
License: MIT License
Classifier: Framework :: Matplotlib
Classifier: License :: OSI Approved :: MIT License
Classifier: Programming Language :: Python :: 3
Requires-Python: >=3.9
Requires-Dist: matplotlib
Requires-Dist: numpy>1.24.4
